{"ammar@gmail.com": {"name": "ammar", "recipients": ["ammar@gmail.com"], "projects": {"pro1": {"sub1": {"session1": {"date": "2023-03-01", "start": "17:29", "end": "17:30", "tasks": {"success": ["task2", "task3"], "fail": ["task1"]}}, "session2": {"date": "2023-03-03", "start": "17:30", "end": "17:35", "tasks": {"success": [], "fail": []}}, "session3": {"date": "2023-02-27", "start": "17:30", "end": "17:36", "tasks": {"success": [], "fail": []}}}}, "pro2": {"sub1": {"session1": {"date": "2023-03-03", "start": "13:37", "end": "13:38", "tasks": {"success": [], "fail": []}}, "session2": {"date": "2023-03-03", "start": "13:38", "end": "", "tasks": {"success": ["task02"], "fail": []}}, "session3": {}, "session4": {}}}}}}